headson/__init__.py
headson/headson.abi3.so
headson-0.15.0.dist-info/METADATA
headson-0.15.0.dist-info/WHEEL
headson-0.15.0.dist-info/licenses/LICENSE
headson-0.15.0.dist-info/RECORD
