Metadata-Version: 2.4
Name: headson
Version: 0.15.0
Classifier: Programming Language :: Python
Classifier: Programming Language :: Python :: 3
Classifier: Programming Language :: Rust
Classifier: Operating System :: OS Independent
Requires-Dist: pytest>=8 ; extra == 'test'
Provides-Extra: test
Summary: Budget‑constrained JSON preview renderer (Python bindings)
Keywords: json,preview,summarize,cli,bindings
Requires-Python: >=3.10
